stegawave/api.py
stegawave/cli.py
stegawave/config.py
stegawave/exceptions.py
stegawave_cli-0.1.0.dist-info/METADATA
stegawave_cli-0.1.0.dist-info/WHEEL
stegawave_cli-0.1.0.dist-info/entry_points.txt
stegawave_cli-0.1.0.dist-info/top_level.txt
stegawave_cli-0.1.0.dist-info/RECORD
